husky_spider_utils/__init__.py
husky_spider_utils/husky_spider.py
husky_spider_utils/selenium_session.py
husky_spider_utils/config/__init__.py
husky_spider_utils/config/spider_config.py
husky_spider_utils/model/__init__.py
husky_spider_utils/model/spider_task.py
husky_spider_utils/tool/__init__.py
husky_spider_utils/tool/dict_tool.py
husky_spider_utils/tool/thread_tools.py
husky_spider_utils/windows/__init__.py
husky_spider_utils/windows/spider_windows.py
husky_spider_utils/windows/pages/__init__.py
husky_spider_utils/windows/pages/config_page.py
husky_spider_utils/windows/pages/log_page.py
husky_spider_utils-0.2.3.data/data/requirements.txt
husky_spider_utils-0.2.3.dist-info/LICENSE
husky_spider_utils-0.2.3.dist-info/METADATA
husky_spider_utils-0.2.3.dist-info/WHEEL
husky_spider_utils-0.2.3.dist-info/top_level.txt
husky_spider_utils-0.2.3.dist-info/RECORD
