Metadata-Version: 2.2
Name: husky-spider-utils
Version: 0.2.3
Summary: Selenium和requests的简单结合实现
Home-page: https://pypi.org/project/husky-spider-utils/
Author: SiberianHusky
Author-email: 3088506834@qq.com
Classifier: Programming Language :: Python :: 3
Classifier: License :: OSI Approved :: MIT License
Classifier: Operating System :: OS Independent
Requires-Python: >=3.10
License-File: LICENSE
Requires-Dist: loguru==0.7.3
Requires-Dist: Requests==2.32.3
Requires-Dist: selenium~=4.29.0
Requires-Dist: webdriver_manager==4.0.2
Requires-Dist: parsel~=1.10.0
Requires-Dist: pyyaml~=6.0.2
Dynamic: author
Dynamic: author-email
Dynamic: classifier
Dynamic: description
Dynamic: description-content-type
Dynamic: home-page
Dynamic: requires-dist
Dynamic: requires-python
Dynamic: summary
